Metadata-Version: 2.4
Name: openedx-django-require
Version: 3.0.0
Summary: A Django staticfiles post-processor for optimizing with RequireJS.
Home-page: https://github.com/etianen/django-require
Author: Dave Hall
Author-email: dave@etianen.com
Maintainer: edX
License: BSD
Classifier: Development Status :: 5 - Production/Stable
Classifier: Environment :: Web Environment
Classifier: Framework :: Django
Classifier: Framework :: Django :: 4.2
Classifier: Intended Audience :: Developers
Classifier: License :: OSI Approved :: BSD License
Classifier: Operating System :: OS Independent
Classifier: Programming Language :: Python
Classifier: Programming Language :: Python :: 3.11
Classifier: Programming Language :: Python :: 3.12
Classifier: Topic :: Internet :: WWW/HTTP
License-File: LICENSE
License-File: LICENSE-BSD-3c
Dynamic: author
Dynamic: author-email
Dynamic: classifier
Dynamic: home-page
Dynamic: license
Dynamic: license-file
Dynamic: maintainer
Dynamic: summary
